{"39": {"becameSuitTime": 1438818306.06, "savedBy": null, "track": "s", "numFloors": 5, "difficulty": 6, "state": "suit", "block": 39}, "40": {"becameSuitTime": 1438818306.059, "savedBy": null, "track": "m", "numFloors": 1, "difficulty": 9, "state": "suit", "block": 40}, "44": {"becameSuitTime": 1438818306.06, "savedBy": null, "track": "c", "numFloors": 3, "difficulty": 6, "state": "suit", "block": 44}, "45": {"becameSuitTime": 1438818306.06, "savedBy": null, "track": "l", "numFloors": 5, "difficulty": 8, "state": "suit", "block": 45}, "13": {"becameSuitTime": 1438818306.059, "savedBy": null, "track": "s", "numFloors": 4, "difficulty": 7, "state": "suit", "block": 13}, "28": {"becameSuitTime": 1438818306.059, "savedBy": null, "track": "m", "numFloors": 5, "difficulty": 6, "state": "suit", "block": 28}}