{"32": {"becameSuitTime": 1438801773.701, "savedBy": null, "track": "s", "numFloors": 0, "difficulty": 2, "state": "cogdo", "block": 32}, "49": {"becameSuitTime": 1438801204.396, "savedBy": null, "track": "s", "numFloors": 0, "difficulty": 1, "state": "cogdo", "block": 49}, "12": {"becameSuitTime": 1438801211.416, "savedBy": null, "track": "s", "numFloors": 0, "difficulty": 2, "state": "cogdo", "block": 12}, "48": {"becameSuitTime": 1438801162.235, "savedBy": null, "track": "m", "numFloors": 3, "difficulty": 3, "state": "suit", "block": 48}, "17": {"becameSuitTime": 1438801162.234, "savedBy": null, "track": "m", "numFloors": 2, "difficulty": 3, "state": "suit", "block": 17}, "19": {"becameSuitTime": 1438801316.124, "savedBy": null, "track": "s", "numFloors": 0, "difficulty": 3, "state": "cogdo", "block": 19}, "58": {"becameSuitTime": 1438801162.235, "savedBy": null, "track": "s", "numFloors": 2, "difficulty": 3, "state": "suit", "block": 58}}